setup.py
pycodesim/__init__.py
pycodesim/sim.py
pycodesim.egg-info/PKG-INFO
pycodesim.egg-info/SOURCES.txt
pycodesim.egg-info/dependency_links.txt
pycodesim.egg-info/requires.txt
pycodesim.egg-info/top_level.txt