Metadata-Version: 1.1
Name: pycodesim
Version: 0.0.2
Summary: A Python Code Similarity Detection Doll, just for fun. 
Home-page: https://github.com/inuyasha2012/pycodesim
Author: inuyasha2012
Author-email: inuyasha021@163.com
License: MIT
Platform: UNKNOWN
Classifier: Programming Language :: Python :: 2.7
Classifier: Programming Language :: Python :: 3
